MANIFEST.in
Makefile
README.rst
requirements.pip
setup.py
django_intranet.egg-info/PKG-INFO
django_intranet.egg-info/SOURCES.txt
django_intranet.egg-info/dependency_links.txt
django_intranet.egg-info/not-zip-safe
django_intranet.egg-info/requires.txt
django_intranet.egg-info/top_level.txt
intranet/__init__.py
intranet/backends.py
intranet/base_forms.py
intranet/base_views.py
intranet/components.py
intranet/forms.py
intranet/models.py
intranet/urls.py
intranet/utils.py
intranet/views.py
intranet/widgets.py
intranet/fixtures/intranet_users.yaml
intranet/locale/fr/LC_MESSAGES/django.mo
intranet/locale/fr/LC_MESSAGES/django.po
intranet/migrations/0001_initial.py
intranet/migrations/__init__.py
intranet/static/css/smoothness/jquery-ui-1.8.17.custom.css
intranet/static/css/smoothness/images/ui-bg_flat_0_aaaaaa_40x100.png
intranet/static/css/smoothness/images/ui-bg_flat_75_ffffff_40x100.png
intranet/static/css/smoothness/images/ui-bg_glass_55_fbf9ee_1x400.png
intranet/static/css/smoothness/images/ui-bg_glass_65_ffffff_1x400.png
intranet/static/css/smoothness/images/ui-bg_glass_75_dadada_1x400.png
intranet/static/css/smoothness/images/ui-bg_glass_75_e6e6e6_1x400.png
intranet/static/css/smoothness/images/ui-bg_glass_95_fef1ec_1x400.png
intranet/static/css/smoothness/images/ui-bg_highlight-soft_75_cccccc_1x100.png
intranet/static/css/smoothness/images/ui-icons_222222_256x240.png
intranet/static/css/smoothness/images/ui-icons_2e83ff_256x240.png
intranet/static/css/smoothness/images/ui-icons_454545_256x240.png
intranet/static/css/smoothness/images/ui-icons_888888_256x240.png
intranet/static/css/smoothness/images/ui-icons_cd0a0a_256x240.png
intranet/static/intranet/bootstrap/css/bootstrap-responsive.css
intranet/static/intranet/bootstrap/css/bootstrap-responsive.min.css
intranet/static/intranet/bootstrap/css/bootstrap.css
intranet/static/intranet/bootstrap/css/bootstrap.min.css
intranet/static/intranet/bootstrap/img/glyphicons-halflings-white.png
intranet/static/intranet/bootstrap/img/glyphicons-halflings.png
intranet/static/intranet/bootstrap/js/bootstrap.js
intranet/static/intranet/bootstrap/js/bootstrap.min.js
intranet/static/intranet/css/intranet.less
intranet/static/intranet/js/csrf.js
