Metadata-Version: 1.1
Name: django-intranet
Version: 0.4
Summary: Intranet made easy
Home-page: http://bitbucket.org/ionyse/django-intranet
Author: Ionyse
Author-email: support@ionyse.com
License: LGPL licence, see LICENSE file
Platform: UNKNOWN
Classifier: Development Status :: 5 - Production/Stable
Classifier: Intended Audience :: Developers
Classifier: Environment :: Web Environment
Classifier: Framework :: Django
Classifier: License :: OSI Approved :: GNU Lesser General Public License v3 (LGPLv3)
Classifier: Natural Language :: English
Classifier: Programming Language :: Python
Classifier: Topic :: Internet :: WWW/HTTP :: WSGI :: Application
